fodcm/__init__.py
fodcm/dcm.py
fodcm/generator.py
fodcm/parser.py
fodcm-0.2.0.dist-info/LICENSE.txt
fodcm-0.2.0.dist-info/METADATA
fodcm-0.2.0.dist-info/WHEEL
fodcm-0.2.0.dist-info/top_level.txt
fodcm-0.2.0.dist-info/RECORD
