Metadata-Version: 2.1
Name: fodcm
Version: 0.2.0
Summary: Far-Out DCM file handler
Home-page: https://gitlab.com/far-out/fodcm.py.git
Author: Jerome Douay
Author-email: jerome@hexamake.com
License: MIT
Project-URL: Documentation, https://pyscaffold.org/
Platform: any
Classifier: Development Status :: 4 - Beta
Classifier: Programming Language :: Python
License-File: LICENSE.txt
Requires-Dist: importlib-metadata ; python_version < "3.8"
Provides-Extra: testing
Requires-Dist: setuptools ; extra == 'testing'
Requires-Dist: pytest ; extra == 'testing'
Requires-Dist: pytest-cov ; extra == 'testing'
